src/__init__.py
src/automaton.py
src/cell.py
src/constants.py
src/csimulation.py
src/entity.py
src/grid.py
src/variables.py
cancer_simulation-0.7.5.dist-info/METADATA
cancer_simulation-0.7.5.dist-info/WHEEL
cancer_simulation-0.7.5.dist-info/entry_points.txt
cancer_simulation-0.7.5.dist-info/top_level.txt
cancer_simulation-0.7.5.dist-info/RECORD
